gambit/__init__.py
gambit/main.py
gambit/algorithms/__init__.py
gambit/algorithms/bird.py
gambit/algorithms/gambit.py
gambit/algorithms/simple.py
gambit_disambig-1.0.5.dist-info/LICENSE.txt
gambit_disambig-1.0.5.dist-info/METADATA
gambit_disambig-1.0.5.dist-info/WHEEL
gambit_disambig-1.0.5.dist-info/top_level.txt
gambit_disambig-1.0.5.dist-info/RECORD
