Metadata-Version: 2.1
Name: gambit-disambig
Version: 1.0.5
Summary: An Open Source name disambiguation tool for version control systems
Home-page: https://github.com/gotec/gambi
Author: Christoph Gote
Author-email: cgote@ethz.ch
License: AGPL-3.0+
Keywords: alias disambiguation,repository mining,version control system
Classifier: Programming Language :: Python :: 3
Classifier: License :: OSI Approved :: GNU Affero General Public License v3 or later (AGPLv3+)
Classifier: Operating System :: OS Independent
License-File: LICENSE.txt
Requires-Dist: pandas>=2.2.2
Requires-Dist: unidecode>=1.3.8
Requires-Dist: python-levenshtein>=0.25.1
Requires-Dist: pyjarowinkler>=1.8
Requires-Dist: tqdm>=4.27.0
Requires-Dist: numpy>=2.0.0
